LICENSE.txt
MANIFEST.in
README.md
setup.cfg
setup.py
krysa/__init__.py
krysa/__main__.py
krysa/dropdown.py
krysa/krysa.kv
krysa/main.py
krysa.egg-info/PKG-INFO
krysa.egg-info/SOURCES.txt
krysa.egg-info/dependency_links.txt
krysa.egg-info/requires.txt
krysa.egg-info/top_level.txt
krysa/data/clock.png
krysa/data/grid.png
krysa/data/head.png
krysa/data/head_data.png
krysa/data/head_image.png
krysa/data/head_plots.png
krysa/data/icon.png
krysa/data/logo.png
krysa/data/star.png
krysa/tasks/__init__.py
krysa/tasks/avgs.py
krysa/tasks/basic.py
krysa/tasks/manipulate.py
krysa/tasks/plot.py
krysa/tasks/tasks.kv
krysa/tests/README.md
krysa/tests/__init__.py
krysa/tests/test_file_closeproject.py
krysa/tests/test_file_exportdata.py
krysa/tests/test_file_importdata.py
krysa/tests/test_file_new.py
krysa/tests/test_file_openproject.py
krysa/tests/test_file_recentprojects.py
krysa/tests/test_file_saveproject.py
krysa/tests/test_tasks_basic_count.py
krysa/tests/test_tasks_basic_countif.py
krysa/tests/test_tasks_basic_freq.py
krysa/tests/test_tasks_basic_large.py
krysa/tests/test_tasks_basic_max.py
krysa/tests/test_tasks_basic_min.py
krysa/tests/test_tasks_basic_small.py
krysa/tests/test_tasks_manipulate_append.py
krysa/tests/test_tasks_plot_lineplot.py
krysa/tests/test_Project/Test.krysa
krysa/tests/test_Project/data/data.sqlite
krysa/tests/test_Project/plots/plot1.png
krysa/tests/test_Project/plots/plot2.png
krysa/tests/test_Project/results/000.png
krysa/tests/test_Project/results/001.png
krysa/tests/test_Project/results/002.png
krysa/tests/test_Project/results/003.png
krysa/utils/__init__.py