Metadata-Version: 1.1
Name: krysa
Version: 0.6.0
Summary: KrySA - Statistical analysis for rats
Home-page: https://github.com/KeyWeeUsr/KrySA
Author: Peter Badida
Author-email: keyweeusr@gmail.com
License: GNU General Public License v3 (GPLv3)
Download-URL: https://github.com/KeyWeeUsr/KrySA/tarball/0.6.0
Keywords: krysa,statistics,kivy
Platform: UNKNOWN
Classifier: Development Status :: 2 - Pre-Alpha
Classifier: Intended Audience :: Education
Classifier: Intended Audience :: Science/Research
Classifier: License :: OSI Approved :: GNU General Public License v3 (GPLv3)
Classifier: Natural Language :: English
Classifier: Operating System :: Android
Classifier: Operating System :: MacOS
Classifier: Operating System :: Microsoft :: Windows
Classifier: Operating System :: POSIX :: Linux
Classifier: Programming Language :: Python
Classifier: Programming Language :: Python :: 2.7
Classifier: Programming Language :: Python :: 3.4
Classifier: Topic :: Scientific/Engineering :: Information Analysis
Classifier: Topic :: Scientific/Engineering :: Visualization
